MultiInputTimeseriesGenerator/__init__.py
MultiInputTimeseriesGenerator/main.py
MultiInputTimeseriesGenerator-0.0.7.dist-info/LICENSE
MultiInputTimeseriesGenerator-0.0.7.dist-info/METADATA
MultiInputTimeseriesGenerator-0.0.7.dist-info/WHEEL
MultiInputTimeseriesGenerator-0.0.7.dist-info/top_level.txt
MultiInputTimeseriesGenerator-0.0.7.dist-info/RECORD
