Metadata-Version: 2.1
Name: MultiInputTimeseriesGenerator
Version: 0.0.7
Summary: UNKNOWN
Home-page: UNKNOWN
Author: Dara Sravan Kumar
Author-email: <sravandara007@gmail.com>
License: UNKNOWN
Keywords: Multi Input,Timeseries Generator,multi input timeseries generator
Platform: UNKNOWN
Classifier: Programming Language :: Python :: 3
Classifier: Operating System :: Unix
Classifier: Operating System :: MacOS :: MacOS X
Classifier: Operating System :: Microsoft :: Windows
License-File: LICENSE
Requires-Dist: tensorflow
Requires-Dist: numpy
